firehot-0.4.1.dist-info/METADATA
firehot-0.4.1.dist-info/WHEEL
firehot/naming.py
firehot/context.py
firehot/embedded/parent_entrypoint.py
firehot/embedded/call_serializer.py
firehot/embedded/child_entrypoint.py
firehot/embedded/types.py
firehot/py.typed
firehot/__tests__/test_naming.py
firehot/__tests__/embedded/test_child_entrypoint.py
firehot/__tests__/embedded/__init__.py
firehot/__tests__/embedded/test_call_serializer.py
firehot/__tests__/embedded/test_parent_entrypoint.py
firehot/__tests__/conftest.py
firehot/__tests__/test_environment.py
firehot/__tests__/__init__.py
firehot/__tests__/test_context.py
firehot/environment.py
firehot/__init__.py
firehot/firehot.cpython-312-aarch64-linux-gnu.so
firehot-0.4.1.dist-info/RECORD
