Metadata-Version: 2.4
Name: firehot
Version: 0.4.1
Classifier: Programming Language :: Python :: 3
Classifier: Programming Language :: Rust
Classifier: License :: OSI Approved :: MIT License
Classifier: Operating System :: OS Independent
Summary: Wicked fast hot reloading
License: MIT
Requires-Python: >=3.10
